{
  "english.pgn": 20,
  "qgambit.pgn": 18,
  "dutch.pgn": 13,
  "benoni.pgn": 38,
  "catalan.pgn": 4,
  "grunfeld.pgn": 24,
  "kid.pgn": 24,
  "veresov.pgn": 11,
  "paleface.pgn": 19,
  "trompowsky.pgn": 11,
  "london.pgn": 11,

  "owen.pgn": 9,
  "sicilian.pgn": 57,
  "caro-kann.pgn": 15,
  "nimzowitsch.pgn": 7,
  "center-counter.pgn": 104,
  "austrian.pgn": 54,
  "pirc.pgn": 65,
  "open.pgn": 4,
  "italian.pgn": 3,
  "scotch.pgn": 7,
  "petrov.pgn": 4,
  "french.pgn": 47,
  "alekhine.pgn": 5,
  "modern.pgn": 4,

  "reti.pgn": 13,
  "bird.pgn": 6,
  "benko.pgn": 5,
  "grob.pgn": 5,
  "misc.pgn": 40,
  "fischer-random.pgn": 13
}